dxkstt/__init__.py
dxkstt-0.1.4.dist-info/METADATA
dxkstt-0.1.4.dist-info/WHEEL
dxkstt-0.1.4.dist-info/top_level.txt
dxkstt-0.1.4.dist-info/RECORD
